pylocalc/__init__.py
pylocalc/models.py
pylocalc-0.5.2.dist-info/LICENSE
pylocalc-0.5.2.dist-info/WHEEL
pylocalc-0.5.2.dist-info/METADATA
pylocalc-0.5.2.dist-info/RECORD
